ai_gcm/__init__.py
ai_gcm/cli.py
ai_gcm/commands/__init__.py
ai_gcm/commands/commit.py
ai_gcm/commands/generate.py
ai_gcm/commands/version.py
ai_gcm/core/__init__.py
ai_gcm/core/models.py
ai_gcm/core/utils.py
ai_gcm-1.0.1.dist-info/LICENSE
ai_gcm-1.0.1.dist-info/METADATA
ai_gcm-1.0.1.dist-info/WHEEL
ai_gcm-1.0.1.dist-info/entry_points.txt
ai_gcm-1.0.1.dist-info/RECORD
