Metadata-Version: 2.3
Name: ai-gcm
Version: 1.0.1
Summary: AI powered Git Commit Message Generator
License: MIT
Keywords: git,commit,ai,ollama
Author: Rahul Katariya
Author-email: rahulkatariya@me.com
Requires-Python: >=3.8,<4.0
Classifier: Development Status :: 5 - Production/Stable
Classifier: Environment :: Console
Classifier: Intended Audience :: Developers
Classifier: License :: OSI Approved :: MIT License
Classifier: Operating System :: OS Independent
Classifier: Programming Language :: Python :: 3
Classifier: Programming Language :: Python :: 3.8
Classifier: Programming Language :: Python :: 3.9
Classifier: Programming Language :: Python :: 3.10
Classifier: Programming Language :: Python :: 3.11
Classifier: Programming Language :: Python :: 3.12
Classifier: Programming Language :: Python :: 3.13
Classifier: Topic :: Software Development :: Version Control :: Git
Requires-Dist: click (>=8.1.7,<9.0.0)
Requires-Dist: ollama (>=0.1.6,<0.2.0)
Requires-Dist: pydantic (>=2.0.0,<3.0.0)
Project-URL: Homepage, https://github.com/zuhlke/ai-gcm
Project-URL: Repository, https://github.com/zuhlke/ai-gcm
